openstack_release_test-8.3.0.dist-info/licenses/AUTHORS
openstack_release_test-8.3.0.dist-info/licenses/LICENSE
release_test/__init__.py
release_test/tests/__init__.py
release_test/tests/base.py
release_test/tests/test_release_test.py
openstack_release_test-8.3.0.dist-info/METADATA
openstack_release_test-8.3.0.dist-info/WHEEL
openstack_release_test-8.3.0.dist-info/pbr.json
openstack_release_test-8.3.0.dist-info/top_level.txt
openstack_release_test-8.3.0.dist-info/RECORD
